d1_cli/__init__.py
d1_cli/dataone.py
d1_cli/version.py
d1_cli/impl/__init__.py
d1_cli/impl/access_control.py
d1_cli/impl/check_dependencies.py
d1_cli/impl/client.py
d1_cli/impl/command_parser.py
d1_cli/impl/command_processor.py
d1_cli/impl/const.py
d1_cli/impl/exceptions.py
d1_cli/impl/format_ids.py
d1_cli/impl/nodes.py
d1_cli/impl/operation_executer.py
d1_cli/impl/operation_formatter.py
d1_cli/impl/operation_maker.py
d1_cli/impl/operation_queue.py
d1_cli/impl/operation_validator.py
d1_cli/impl/replication_policy.py
d1_cli/impl/session.py
d1_cli/impl/system_metadata.py
d1_cli/impl/util.py
d1_cli/tests/__init__.py
d1_cli/tests/test_access_control.py
d1_cli/tests/test_cli.py
d1_cli/tests/test_cli_exceptions.py
d1_cli/tests/test_cli_util.py
d1_cli/tests/test_command_processor.py
d1_cli/tests/test_replication_policy.py
d1_cli/tests/test_session.py
dataone.cli-3.5.2.dist-info/METADATA
dataone.cli-3.5.2.dist-info/WHEEL
dataone.cli-3.5.2.dist-info/entry_points.txt
dataone.cli-3.5.2.dist-info/top_level.txt
dataone.cli-3.5.2.dist-info/RECORD
