Metadata-Version: 2.1
Name: dataone.cli
Version: 3.5.2
Summary: Command-Line Interface (CLI) for DataONE
Home-page: https://github.com/DataONEorg/d1_python
Author: DataONE Project
Author-email: developers@dataone.org
License: Apache License, Version 2.0
Keywords: DataONE cli command line member-node coordinating-node
Classifier: Development Status :: 5 - Production/Stable
Classifier: Intended Audience :: Developers
Classifier: Topic :: Scientific/Engineering
Classifier: License :: OSI Approved :: Apache Software License
Classifier: Programming Language :: Python :: 3
Classifier: Programming Language :: Python :: 3.7
Requires-Dist: dataone.common (>=3.5.2)
Requires-Dist: dataone.libclient (>=3.5.2)
Requires-Dist: requests (>=2.31.0)
